oakfs/__init__.py
oakfs/cli.py
oakfs/filesystem.py
oakfs/logroller.py
oakfs/oak.py
oakfs-0.5.3.dist-info/METADATA
oakfs-0.5.3.dist-info/WHEEL
oakfs-0.5.3.dist-info/entry_points.txt
oakfs-0.5.3.dist-info/licenses/LICENSE
oakfs-0.5.3.dist-info/RECORD
