Metadata-Version: 2.4
Name: oakfs
Version: 0.5.3
Summary: A humane CLI-based filesystem exploration tool, for humans.
License-Expression: MIT
License-File: LICENSE
Author: Ritchie Mwewa
Author-email: rly0nheart@duck.com
Requires-Python: >=3.12,<4.0
Classifier: Development Status :: 4 - Beta
Classifier: Programming Language :: Python :: 3
Classifier: Intended Audience :: End Users/Desktop
Classifier: Operating System :: OS Independent
Classifier: License :: OSI Approved :: MIT License
Classifier: Natural Language :: English
Requires-Dist: humanize (>=4.13.0,<5.0.0)
Requires-Dist: puremagic (>=1.30,<2.0)
Requires-Dist: rich-click (>=1.8.9,<2.0.0)
Project-URL: issues, https://github.com/rly0nheart/oakfs/issues
Project-URL: repository, https://github.com/rly0nheart/oakfs
